bad_otzyvy_net/__init__.py
bad_otzyvy_net/bad_otzyvy_net.py
bad_otzyvy_net-0.1.2.dist-info/LICENSE
bad_otzyvy_net-0.1.2.dist-info/METADATA
bad_otzyvy_net-0.1.2.dist-info/WHEEL
bad_otzyvy_net-0.1.2.dist-info/top_level.txt
bad_otzyvy_net-0.1.2.dist-info/RECORD
